[{"pk": 2, "model": "flatpages.flatpage", "fields": {"registration_required": false, "title": "Eta Kappa Nu (HKN), Mu Chapter - About", "url": "/about/", "template_name": "", "sites": [1], "content": "Coming Soon!", "enable_comments": false}}, {"pk": 1, "model": "flatpages.flatpage", "fields": {"registration_required": false, "title": "Eta Kappa Nu (HKN), Mu Chapter - About - Contact Us", "url": "/about/contact/", "template_name": "", "sites": [1], "content": "<h1>Contact Us</h1>\r\n<div style=\"width: 100%\">\r\n<table>\r\n    <tr>\r\n        <th style=\"width: 33%\">\r\n            Email\r\n        </th>\r\n        <th style=\"width: 33%\">\r\n            Mail\r\n        </th>\r\n        <th style=\"width: 33%\">\r\n            In Person\r\n        </th>\r\n    </tr>\r\n    <tr>\r\n        <td>\r\n            <ul>\r\n                <li>\r\n                    General\r\n                </li>\r\n                hkn@hkn.eecs.berkeley.edu\r\n                <li>\r\n                    Industrial Relations\r\n                </li>\r\n                indrel@hkn.eecs.berkeley.edu\r\n                <li>\r\n                    Webmaster\r\n                </li>\r\n                www@hkn.eecs.berkeley.edu\r\n            </ul>\r\n        </td>\r\n        <td>\r\n            Eta Kappa Nu\r\n            <br>\r\n            290 Cory Hall\r\n            <br>\r\n            UC Berkeley\r\n            <br>\r\n            Berkeley, CA 94720\r\n            <br>\r\n        </td>\r\n        <td>\r\n            290 Cory Hall\r\n            <br>\r\n            (510) 642-7346\r\n            <br>\r\n            <br>\r\n            345 Soda Hall\r\n            <br>\r\n            (510) 642-9952\r\n            <br>\r\n        </td>\r\n    </tr>\r\n</table>\r\n</div>", "enable_comments": false}}, {"pk": 6, "model": "flatpages.flatpage", "fields": {"registration_required": false, "title": "Eta Kappa Nu (HKN), Mu Chapter - Alumni - Newsletter", "url": "/alumni/newsletter/", "template_name": "", "sites": [1], "content": "<p>Coming Soon!</p>", "enable_comments": false}}, {"pk": 5, "model": "flatpages.flatpage", "fields": {"registration_required": false, "title": "Eta Kappa Nu (HKN), Mu Chapter - Alumni - Registration", "url": "/alumni/registration/", "template_name": "", "sites": [1], "content": "<p>Coming Soon!</p>", "enable_comments": false}}, {"pk": 4, "model": "flatpages.flatpage", "fields": {"registration_required": false, "title": "Eta Kappa Nu (HKN), Mu Chapter - Student Services - Faculty Retreat", "url": "/services/facret/", "template_name": "", "sites": [1], "content": "<h1>Faculty Retreat Presentation</h1>\r\n\r\n<p>\r\nEach year, HKN and several other student groups deliver a presentation to the EECS faculty.\r\n</p>\r\n\r\n<ul>\r\n\t<li>\r\n\t\t<a href=\"/files/content/facret/2000retreat.ppt\">\r\n\t\t\t2000 Presentation\r\n\t\t</a>\r\n\t</li>\r\n\t<li>\r\n\t\t<a href=\"/files/content/facret/2001retreat.ppt\">\r\n\t\t\t2001 Presentation\r\n\t\t</a>\r\n\t</li>\r\n\t<li>\r\n\t\t<a href=\"/files/content/facret/2002retreat.ppt\">\r\n\t\t\t2002 Presentation\r\n\t\t</a>\r\n\t</li>\r\n\t<li>\r\n\t\t<a href=\"/files/content/facret/2003retreat.ppt\">\r\n\t\t\t2003 Presentation\r\n\t\t</a>\r\n\t</li>\r\n\t<li>\r\n\t\t<a href=\"/files/content/facret/2004retreat.ppt\">\r\n\t\t\t2004 Presentation\r\n\t\t</a>\r\n\t</li>\r\n\t<li>\r\n\t\t<a href=\"/files/content/facret/2005retreat.ppt\">\r\n\t\t\t2005 Presentation\r\n\t\t</a>\r\n\t</li>\r\n\t<li>\r\n\t\t<a href=\"/files/content/facret/2006retreat.ppt\">\r\n\t\t\t2006 Presentation\r\n\t\t</a>\r\n\t</li>\r\n\t<li>\r\n\t\t<a href=\"/files/content/facret/2007retreat.ppt\">\r\n\t\t\t2007 Presentation\r\n\t\t</a>\r\n\t</li>\r\n\t<li>\r\n\t\t<a href=\"/files/content/facret/2008retreat.ppt\">\r\n\t\t\t2008 Presentation\r\n\t\t</a>\r\n\t</li>\r\n</ul>", "enable_comments": false}}, {"pk": 3, "model": "flatpages.flatpage", "fields": {"registration_required": false, "title": "Landing Page Content", "url": "landing-page", "template_name": "", "sites": [1], "content": "<div>\r\n<p>Eta Kappa Nu (HKN) is the national Electrical Engineering honor society.\r\nThe Berkeley chapter is among the most active engineering societies at Berkeley, providing academic services to fellow undergraduates.\r\nOur two offices are located in 290 Cory and 345 Soda near the northeastern corner of the UC Berkeley campus.</p>\r\n\r\n    <img src=\"{{MEDIA_URL}}content/main/tutoring.jpg\" style=\"float: right; padding: 10px 0px 10px 20px;\"/>\r\n    <h1>Student Services</h1>\r\n\r\n    <h2>Tutoring</h2>\r\n<p>\r\n    Students who need advice or tutoring in EE and CS courses are encouraged to drop by for free assistance. Officers hold office hours from 11am to 5pm every weekday.\r\n</p>\r\n\r\n    <h2>Exam Preparation</h2>\r\n<p>\r\n    HKN provides a database of past exams and review problems to prepare students for midterms and finals. In addition, look out for exam review sessions for lower-division courses.\r\n</p>\r\n\r\n    <h2>Course Surveys and Peer Advising</h2>\r\n<p>\r\n    HKN conducts course surveys for all classes offered by the EECS department every semester. The results for all professors and TAs who have opted-in are available online. Students who need more advice in choosing classes are encouraged to consult our officers during office hours.\r\n</p>\r\n\r\n\r\n    <img src=\"{{MEDIA_URL}}content/main/career_fair.jpg\" style=\"float: left; padding: 10px 20px 10px 0px;\"/>\r\n    <h1>Industry Relations</h1>\r\n<p>\r\n    HKN has strong ties with industry, linking students with companies by setting up info sessions where companies can give a presentation about themselves and provide a forum for students to talk to industry and find out more about the work environment. Additionally, we sell resume books containing the resumes of our members.\r\n</p>\r\n\r\n    <h1>Membership</h1>\r\n<p>\r\n    Membership in Eta Kappa Nu is extended to undergraduates in the top fourth of the junior class and the top third of the senior class in EECS, and all continuing EE graduate students. Interested students should watch for the list of eligible names, which is posted around Cory Hall at the beginning of each semester. After being invited to join, prospective members participate in projects and social activities that demonstrate their dedication to serving fellow members of the EECS community, the ultimate goal of HKN.\r\n</p>\r\n    </div>\r\n", "enable_comments": false}}]
